alpacax/__init__.py
alpacax/cli.py
alpacax-0.1.0.dist-info/licenses/LICENSE
alpacax-0.1.0.dist-info/METADATA
alpacax-0.1.0.dist-info/WHEEL
alpacax-0.1.0.dist-info/entry_points.txt
alpacax-0.1.0.dist-info/top_level.txt
alpacax-0.1.0.dist-info/RECORD
