Metadata-Version: 2.4
Name: alpacax
Version: 0.1.0
Summary: LoRA-powered GPT2 AlpacaX CLI
Home-page: https://github.com/SullyGreene/AlpacaX
Author: Sully Greene
Classifier: Programming Language :: Python :: 3
Classifier: License :: OSI Approved :: MIT License
Requires-Python: >=3.8
License-File: LICENSE
Requires-Dist: transformers>=4.36.2
Requires-Dist: peft>=0.9.0
Requires-Dist: accelerate>=0.27.2
Requires-Dist: bitsandbytes>=0.42.0
Requires-Dist: torch>=2.1.0
Dynamic: author
Dynamic: classifier
Dynamic: description
Dynamic: description-content-type
Dynamic: home-page
Dynamic: license-file
Dynamic: requires-dist
Dynamic: requires-python
Dynamic: summary
